dash_dynamic_grid_layout/DashGridCol.py
dash_dynamic_grid_layout/DashGridLayout.py
dash_dynamic_grid_layout/DraggableWrapper.py
dash_dynamic_grid_layout/__init__.py
dash_dynamic_grid_layout/_imports_.py
dash_dynamic_grid_layout/dash_dynamic_grid_layout.min.js
dash_dynamic_grid_layout/dash_dynamic_grid_layout.min.js.map
dash_dynamic_grid_layout/dash_grid_layout.min.js
dash_dynamic_grid_layout/dash_grid_layout.min.js.map
dash_dynamic_grid_layout/metadata.json
dash_dynamic_grid_layout/package-info.json
dash_dynamic_grid_layout-0.1.3.dist-info/LICENSE
dash_dynamic_grid_layout-0.1.3.dist-info/METADATA
dash_dynamic_grid_layout-0.1.3.dist-info/WHEEL
dash_dynamic_grid_layout-0.1.3.dist-info/top_level.txt
dash_dynamic_grid_layout-0.1.3.dist-info/RECORD
