Metadata-Version: 2.2
Name: dash_dynamic_grid_layout
Version: 0.1.3
Summary: Grid layout system for moving components around.
Author: pipinstallpython <pipinstallpython@gmail.com>
License: MIT
Classifier: Framework :: Dash
License-File: LICENSE
Dynamic: author
Dynamic: classifier
Dynamic: description
Dynamic: description-content-type
Dynamic: license
Dynamic: summary
